polta/__init__.py
polta/check.py
polta/checks/__init__.py
polta/checks/not_null_or_empty.py
polta/checks/positive_int.py
polta/checks/value_in.py
polta/enums.py
polta/exceptions.py
polta/exporter.py
polta/ingester.py
polta/maps.py
polta/metastore.py
polta/pipe.py
polta/pipeline.py
polta/schemas/__init__.py
polta/schemas/ingester.py
polta/schemas/system.py
polta/schemas/table.py
polta/serializers.py
polta/table.py
polta/table_schema.py
polta/test.py
polta/transformer.py
polta/types.py
polta/udfs.py
polta-0.8.4.dist-info/LICENSE
polta-0.8.4.dist-info/METADATA
polta-0.8.4.dist-info/NOTICE.md
polta-0.8.4.dist-info/WHEEL
polta-0.8.4.dist-info/RECORD
