Metadata-Version: 2.3
Name: polta
Version: 0.8.4
Summary: Data engineering tool combining Polars transformations with Delta tables/lakes
License: MIT
Author: JoshTG
Requires-Python: >=3.13
Classifier: License :: OSI Approved :: MIT License
Classifier: Programming Language :: Python :: 3
Classifier: Programming Language :: Python :: 3.13
Requires-Dist: deltalake (>=0.25.0,<1.0.0)
Requires-Dist: ipykernel (>=6.29.5,<7.0.0)
Requires-Dist: openpyxl (>=3.1.5,<3.2.0)
Requires-Dist: pip (>=25.1.1,<25.2.0)
Requires-Dist: polars (>=1.30.0,<1.31.0)
Requires-Dist: pytest (>=8.3.5,<8.4.0)
Requires-Dist: pytest-cov (>=6.2.1,<6.3.0)
Requires-Dist: ruff (>=0.12.3,<0.13.0)
Requires-Dist: tzdata (>=2025.2,<2026.1)
